uw_attest/VERSION
uw_attest/__init__.py
uw_attest/dao.py
uw_attest/models.py
uw_attest/test.py
uw_attest/utils.py
uw_attest/resources/attest/file/attestations/v1/covid19/9136CCB8F66711D5BE060004AC494F31
uw_attest/resources/attest/file/attestations/v1/covid19/9136CCB8F66711D5BE060004AC494FFE
uw_attest/resources/attest_auth/file/oauth2/token.POST
uw_attest/tests/__init__.py
uw_attest/tests/test_attest.py
uw_attest/tests/test_dao.py
UW_RestClients_Attest-0.1.dist-info/LICENSE
UW_RestClients_Attest-0.1.dist-info/METADATA
UW_RestClients_Attest-0.1.dist-info/WHEEL
UW_RestClients_Attest-0.1.dist-info/top_level.txt
UW_RestClients_Attest-0.1.dist-info/RECORD
