Metadata-Version: 2.1
Name: UW-RestClients-Attest
Version: 0.1
Summary: A library for connecting to HFS services at the University of Washington
Home-page: https://github.com/uw-it-aca/uw-restclients-attest
Author: UW-IT AXDD
Author-email: aca-it@uw.edu
License: Apache License, Version 2.0
Platform: UNKNOWN
Classifier: Intended Audience :: Developers
Classifier: License :: OSI Approved :: Apache Software License
Classifier: Operating System :: OS Independent
Classifier: Programming Language :: Python
Classifier: Programming Language :: Python :: 3.6
Requires-Dist: UW-RestClients-Core
Requires-Dist: mock
